<PAGEDATA>
<PAGE ASSIGN="\\HORNET\ImageQueue\FILE23359858" NUM="2" NAME="file271.tif" MARK="NONE" DATE="-100000" ADMISSION="1"/>
<PAGE ASSIGN="\\HORNET\ImageQueue\FILE23359858" NUM="3" NAME="file272.tif" MARK="NONE" DATE="-100000" ADMISSION="1"/>
<PAGE ASSIGN="\\HORNET\ImageQueue\FILE23359858" NUM="4" NAME="file273.tif" MARK="NONE" DATE="-100000" ADMISSION="1"/>
<PAGE ASSIGN="\\HORNET\ImageQueue\FILE23359858" NUM="5" NAME="file274.tif" MARK="NONE" DATE="-100000" ADMISSION="1"/>
<PAGE ASSIGN="\\HORNET\ImageQueue\FILE23359858" NUM="6" NAME="file275.tif" MARK="NONE" DATE="-100000" ADMISSION="1"/>
<PAGE ASSIGN="\\HORNET\ImageQueue\FILE23359858" NUM="7" NAME="file276.tif" MARK="NONE" DATE="-100000" ADMISSION="1"/>
<PAGE ASSIGN="\\HORNET\ImageQueue\FILE23359858" NUM="8" NAME="file277.tif" MARK="NONE" DATE="-100000" ADMISSION="1"/>
<PAGE ASSIGN="\\HORNET\ImageQueue\FILE23359858" NUM="9" NAME="file278.tif" MARK="NONE" DATE="-100000" ADMISSION="1"/>
<PAGE ASSIGN="\\HORNET\ImageQueue\FILE23359858" NUM="10" NAME="file279.tif" MARK="NONE" DATE="-100000" ADMISSION="1"/>
<PAGE ASSIGN="\\HORNET\ImageQueue\FILE23359858" NUM="11" NAME="file280.tif" MARK="NONE" DATE="-100000" ADMISSION="1"/>
<PAGE ASSIGN="\\HORNET\ImageQueue\FILE23359858" NUM="12" NAME="file281.tif" MARK="NONE" DATE="-100000" ADMISSION="1"/>
<PAGE ASSIGN="\\HORNET\ImageQueue\FILE23359858" NUM="13" NAME="file282.tif" MARK="NONE" DATE="-100000" ADMISSION="1"/>
<PAGE ASSIGN="\\HORNET\ImageQueue\FILE23359858" NUM="14" NAME="file283.tif" MARK="NONE" DATE="-100000" ADMISSION="1"/>
<PAGE ASSIGN="\\HORNET\ImageQueue\FILE23359858" NUM="15" NAME="file284.tif" MARK="NONE" DATE="-100000" ADMISSION="1"/>
<PAGE ASSIGN="\\HORNET\ImageQueue\FILE23359858" NUM="16" NAME="file285.tif" MARK="NONE" DATE="-100000" ADMISSION="1"/>
<PAGE ASSIGN="\\HORNET\ImageQueue\FILE23359858" NUM="17" NAME="file286.tif" MARK="NONE" DATE="-100000" ADMISSION="1"/>
<PAGE ASSIGN="\\HORNET\ImageQueue\FILE23359858" NUM="18" NAME="file287.tif" MARK="NONE" DATE="-100000" ADMISSION="1"/>
<PAGE ASSIGN="\\HORNET\ImageQueue\FILE23359858" NUM="19" NAME="file288.tif" MARK="NONE" DATE="-100000" ADMISSION="1"/>
<PAGE ASSIGN="\\HORNET\ImageQueue\FILE23359858" NUM="20" NAME="file289.tif" MARK="NONE" DATE="-100000" ADMISSION="1"/>
<PAGE ASSIGN="\\HORNET\ImageQueue\FILE23359858" NUM="21" NAME="file290.tif" MARK="NONE" DATE="-100000" ADMISSION="1"/>
<PAGE ASSIGN="\\HORNET\ImageQueue\FILE23359858" NUM="22" NAME="file291.tif" MARK="NONE" DATE="-100000" ADMISSION="1"/>
<PAGE ASSIGN="\\HORNET\ImageQueue\FILE23359858" NUM="23" NAME="file292.tif" MARK="NONE" DATE="-100000" ADMISSION="1"/>
<PAGE ASSIGN="\\HORNET\ImageQueue\FILE23359858" NUM="24" NAME="file293.tif" MARK="NONE" DATE="-100000" ADMISSION="1"/>
<PAGE ASSIGN="\\HORNET\ImageQueue\FILE23359858" NUM="25" NAME="file294.tif" MARK="NONE" DATE="-100000" ADMISSION="1"/>
<PAGE ASSIGN="\\HORNET\ImageQueue\FILE23359858" NUM="26" NAME="file295.tif" MARK="NONE" DATE="-100000" ADMISSION="1"/>
<PAGE ASSIGN="\\HORNET\ImageQueue\FILE23359858" NUM="27" NAME="file296.tif" MARK="NONE" DATE="-100000" ADMISSION="1"/>
<PAGE ASSIGN="\\HORNET\ImageQueue\FILE23359858" NUM="28" NAME="file297.tif" MARK="NONE" DATE="-100000" ADMISSION="1"/>
<PAGE ASSIGN="\\HORNET\ImageQueue\FILE23359858" NUM="29" NAME="file298.tif" MARK="NONE" DATE="-100000" ADMISSION="1"/>
<PAGE ASSIGN="\\HORNET\ImageQueue\FILE23359858" NUM="30" NAME="file299.tif" MARK="NONE" DATE="-100000" ADMISSION="1"/>
<PAGE ASSIGN="\\HORNET\ImageQueue\FILE23359858" NUM="31" NAME="file300.tif" MARK="NONE" DATE="-100000" ADMISSION="1"/>
<PAGE ASSIGN="\\HORNET\ImageQueue\FILE23359858" NUM="32" NAME="file301.tif" MARK="NONE" DATE="-100000" ADMISSION="1"/>
<PAGE ASSIGN="\\HORNET\ImageQueue\FILE23359858" NUM="33" NAME="file302.tif" MARK="NONE" DATE="-100000" ADMISSION="1"/>
<PAGE ASSIGN="\\HORNET\ImageQueue\FILE23359858" NUM="34" NAME="file303.tif" MARK="NONE" DATE="-100000" ADMISSION="1"/>
<PAGE ASSIGN="\\HORNET\ImageQueue\FILE23359858" NUM="35" NAME="file304.tif" MARK="NONE" DATE="-100000" ADMISSION="1"/>
<PAGE ASSIGN="\\HORNET\ImageQueue\FILE23359858" NUM="36" NAME="file305.tif" MARK="NONE" DATE="-100000" ADMISSION="1"/>
<PAGE ASSIGN="\\HORNET\ImageQueue\FILE23359858" NUM="37" NAME="file306.tif" MARK="NONE" DATE="-100000" ADMISSION="1"/>
<PAGE ASSIGN="\\HORNET\ImageQueue\FILE23359858" NUM="38" NAME="file307.tif" MARK="NONE" DATE="-100000" ADMISSION="1"/>
<PAGE ASSIGN="\\HORNET\ImageQueue\FILE23359858" NUM="39" NAME="file308.tif" MARK="NONE" DATE="-100000" ADMISSION="1"/>
<PAGE ASSIGN="\\HORNET\ImageQueue\FILE23359858" NUM="40" NAME="file309.tif" MARK="NONE" DATE="-100000" ADMISSION="1"/>
<PAGE ASSIGN="\\HORNET\ImageQueue\FILE23359858" NUM="41" NAME="file310.tif" MARK="NONE" DATE="-100000" ADMISSION="1"/>
<PAGE ASSIGN="\\HORNET\ImageQueue\FILE23359858" NUM="42" NAME="file311.tif" MARK="NONE" DATE="-100000" ADMISSION="1"/>
<PAGE ASSIGN="\\HORNET\ImageQueue\FILE23359858" NUM="43" NAME="file312.tif" MARK="NONE" DATE="-100000" ADMISSION="1"/>
<PAGE ASSIGN="\\HORNET\ImageQueue\FILE23359858" NUM="44" NAME="file313.tif" MARK="NONE" DATE="-100000" ADMISSION="1"/>
<PAGE ASSIGN="\\HORNET\ImageQueue\FILE23359858" NUM="45" NAME="file314.tif" MARK="NONE" DATE="-100000" ADMISSION="1"/>
<PAGE ASSIGN="\\HORNET\ImageQueue\FILE23359858" NUM="46" NAME="file315.tif" MARK="NONE" DATE="-100000" ADMISSION="1"/>
<PAGE ASSIGN="\\HORNET\ImageQueue\FILE23359858" NUM="47" NAME="file316.tif" MARK="NONE" DATE="-100000" ADMISSION="1"/>
<PAGE ASSIGN="\\HORNET\ImageQueue\FILE23359858" NUM="48" NAME="file317.tif" MARK="NONE" DATE="-100000" ADMISSION="1"/>
<PAGE ASSIGN="\\HORNET\ImageQueue\FILE23359858" NUM="49" NAME="file318.tif" MARK="NONE" DATE="-100000" ADMISSION="1"/>
<PAGE ASSIGN="\\HORNET\ImageQueue\FILE23359858" NUM="50" NAME="file319.tif" MARK="NONE" DATE="-100000" ADMISSION="1"/>
<PAGE ASSIGN="\\HORNET\ImageQueue\FILE23359858" NUM="51" NAME="file320.tif" MARK="NONE" DATE="-100000" ADMISSION="1"/>
<PAGE ASSIGN="\\HORNET\ImageQueue\FILE23359858" NUM="52" NAME="file321.tif" MARK="NONE" DATE="-100000" ADMISSION="1"/>
<PAGE ASSIGN="\\HORNET\ImageQueue\FILE23359858" NUM="53" NAME="file322.tif" MARK="NONE" DATE="-100000" ADMISSION="1"/>
<PAGE ASSIGN="\\HORNET\ImageQueue\FILE23359858" NUM="54" NAME="file323.tif" MARK="NONE" DATE="-100000" ADMISSION="1"/>
<PAGE ASSIGN="\\HORNET\ImageQueue\FILE23359858" NUM="55" NAME="file324.tif" MARK="NONE" DATE="-100000" ADMISSION="1"/>
<PAGE ASSIGN="\\HORNET\ImageQueue\FILE23359858" NUM="56" NAME="file325.tif" MARK="NONE" DATE="-100000" ADMISSION="1"/>
<PAGE ASSIGN="\\HORNET\ImageQueue\FILE23359858" NUM="57" NAME="file326.tif" MARK="NONE" DATE="-100000" ADMISSION="1"/>
<PAGE ASSIGN="\\HORNET\ImageQueue\FILE23359858" NUM="58" NAME="file327.tif" MARK="NONE" DATE="-100000" ADMISSION="1"/>
<PAGE ASSIGN="\\HORNET\ImageQueue\FILE23359858" NUM="59" NAME="file328.tif" MARK="NONE" DATE="-100000" ADMISSION="1"/>
<PAGE ASSIGN="\\HORNET\ImageQueue\FILE23359858" NUM="60" NAME="file329.tif" MARK="NONE" DATE="-100000" ADMISSION="1"/>
<PAGE ASSIGN="\\HORNET\ImageQueue\FILE23359858" NUM="61" NAME="file330.tif" MARK="NONE" DATE="-100000" ADMISSION="1"/>
<PAGE ASSIGN="\\HORNET\ImageQueue\FILE23359858" NUM="62" NAME="file331.tif" MARK="NONE" DATE="-100000" ADMISSION="1"/>
<PAGE ASSIGN="\\HORNET\ImageQueue\FILE23359858" NUM="63" NAME="file332.tif" MARK="NONE" DATE="-100000" ADMISSION="1"/>
<PAGE ASSIGN="\\HORNET\ImageQueue\FILE23359858" NUM="64" NAME="file333.tif" MARK="NONE" DATE="-100000" ADMISSION="1"/>
<PAGE ASSIGN="\\HORNET\ImageQueue\FILE23359858" NUM="65" NAME="file334.tif" MARK="NONE" DATE="-100000" ADMISSION="1"/>
<PAGE ASSIGN="\\HORNET\ImageQueue\FILE23359858" NUM="66" NAME="file335.tif" MARK="NONE" DATE="-100000" ADMISSION="1"/>
<PAGE ASSIGN="\\HORNET\ImageQueue\FILE23359858" NUM="67" NAME="file336.tif" MARK="NONE" DATE="-100000" ADMISSION="1"/>
<PAGE ASSIGN="\\HORNET\ImageQueue\FILE23359858" NUM="68" NAME="file337.tif" MARK="NONE" DATE="-100000" ADMISSION="1"/>
<PAGE ASSIGN="\\HORNET\ImageQueue\FILE23359858" NUM="69" NAME="file338.tif" MARK="NONE" DATE="-100000" ADMISSION="1"/>
<PAGE ASSIGN="\\HORNET\ImageQueue\FILE23359858" NUM="70" NAME="file339.tif" MARK="NONE" DATE="-100000" ADMISSION="1"/>
<PAGE ASSIGN="\\HORNET\ImageQueue\FILE23359858" NUM="71" NAME="file340.tif" MARK="NONE" DATE="-100000" ADMISSION="1"/>
<PAGE ASSIGN="\\HORNET\ImageQueue\FILE23359858" NUM="72" NAME="file341.tif" MARK="NONE" DATE="-100000" ADMISSION="1"/>
<PAGE ASSIGN="\\HORNET\ImageQueue\FILE23359858" NUM="73" NAME="file342.tif" MARK="NONE" DATE="-100000" ADMISSION="1"/>
<PAGE ASSIGN="\\HORNET\ImageQueue\FILE23359858" NUM="74" NAME="file343.tif" MARK="NONE" DATE="-100000" ADMISSION="1"/>
<PAGE ASSIGN="\\HORNET\ImageQueue\FILE23359858" NUM="75" NAME="file344.tif" MARK="NONE" DATE="-100000" ADMISSION="1"/>
<PAGE ASSIGN="\\HORNET\ImageQueue\FILE23359858" NUM="76" NAME="file345.tif" MARK="NONE" DATE="-100000" ADMISSION="1"/>
<PAGE ASSIGN="\\HORNET\ImageQueue\FILE23359858" NUM="77" NAME="file346.tif" MARK="NONE" DATE="-100000" ADMISSION="1"/>
<PAGE ASSIGN="\\HORNET\ImageQueue\FILE23359858" NUM="78" NAME="file347.tif" MARK="NONE" DATE="-100000" ADMISSION="1"/>
<PAGE ASSIGN="\\HORNET\ImageQueue\FILE23359858" NUM="79" NAME="file348.tif" MARK="NONE" DATE="-100000" ADMISSION="1"/>
<PAGE ASSIGN="\\HORNET\ImageQueue\FILE23359858" NUM="80" NAME="file349.tif" MARK="NONE" DATE="-100000" ADMISSION="1"/>
<PAGE ASSIGN="\\HORNET\ImageQueue\FILE23359858" NUM="81" NAME="file350.tif" MARK="NONE" DATE="-100000" ADMISSION="1"/>
<PAGE ASSIGN="\\HORNET\ImageQueue\FILE23359858" NUM="82" NAME="file351.tif" MARK="NONE" DATE="-100000" ADMISSION="1"/>
<PAGE ASSIGN="\\HORNET\ImageQueue\FILE23359858" NUM="83" NAME="file352.tif" MARK="NONE" DATE="-100000" ADMISSION="1"/>
<PAGE ASSIGN="\\HORNET\ImageQueue\FILE23359858" NUM="84" NAME="file353.tif" MARK="NONE" DATE="-100000" ADMISSION="1"/>
<PAGE ASSIGN="\\HORNET\ImageQueue\FILE23359858" NUM="85" NAME="file354.tif" MARK="NONE" DATE="-100000" ADMISSION="1"/>
<PAGE ASSIGN="\\HORNET\ImageQueue\FILE23359858" NUM="86" NAME="file355.tif" MARK="NONE" DATE="-100000" ADMISSION="1"/>
<PAGE ASSIGN="\\HORNET\ImageQueue\FILE23359858" NUM="87" NAME="file356.tif" MARK="NONE" DATE="-100000" ADMISSION="1"/>
<PAGE ASSIGN="\\HORNET\ImageQueue\FILE23359858" NUM="88" NAME="file357.tif" MARK="NONE" DATE="-100000" ADMISSION="1"/>
<PAGE ASSIGN="\\HORNET\ImageQueue\FILE23359858" NUM="89" NAME="file358.tif" MARK="NONE" DATE="-100000" ADMISSION="1"/>
<PAGE ASSIGN="\\HORNET\ImageQueue\FILE23359858" NUM="90" NAME="file359.tif" MARK="NONE" DATE="-100000" ADMISSION="1"/>
<PAGE ASSIGN="\\HORNET\ImageQueue\FILE23359858" NUM="91" NAME="file360.tif" MARK="NONE" DATE="-100000" ADMISSION="1"/>
<PAGE ASSIGN="\\HORNET\ImageQueue\FILE23359858" NUM="92" NAME="file361.tif" MARK="NONE" DATE="-100000" ADMISSION="1"/>
<PAGE ASSIGN="\\HORNET\ImageQueue\FILE23359858" NUM="93" NAME="file362.tif" MARK="NONE" DATE="-100000" ADMISSION="1"/>
<PAGE ASSIGN="\\HORNET\ImageQueue\FILE23359858" NUM="94" NAME="file363.tif" MARK="NONE" DATE="-100000" ADMISSION="1"/>
<PAGE ASSIGN="\\HORNET\ImageQueue\FILE23359858" NUM="95" NAME="file364.tif" MARK="NONE" DATE="-100000" ADMISSION="1"/>
<PAGE ASSIGN="\\HORNET\ImageQueue\FILE23359858" NUM="96" NAME="file365.tif" MARK="NONE" DATE="-100000" ADMISSION="1"/>
<PAGE ASSIGN="\\HORNET\ImageQueue\FILE23359858" NUM="97" NAME="file366.tif" MARK="NONE" DATE="-100000" ADMISSION="1"/>
<PAGE ASSIGN="\\HORNET\ImageQueue\FILE23359858" NUM="98" NAME="file367.tif" MARK="NONE" DATE="-100000" ADMISSION="1"/>
<PAGE ASSIGN="\\HORNET\ImageQueue\FILE23359858" NUM="99" NAME="file368.tif" MARK="NONE" DATE="-100000" ADMISSION="1"/>
<PAGE ASSIGN="\\HORNET\ImageQueue\FILE23359858" NUM="100" NAME="file369.tif" MARK="NONE" DATE="-100000" ADMISSION="1"/>
<PAGE ASSIGN="\\HORNET\ImageQueue\FILE23359858" NUM="101" NAME="file370.tif" MARK="NONE" DATE="-100000" ADMISSION="1"/>
<PAGE ASSIGN="\\HORNET\ImageQueue\FILE23359858" NUM="102" NAME="file371.tif" MARK="NONE" DATE="-100000" ADMISSION="1"/>
<PAGE ASSIGN="\\HORNET\ImageQueue\FILE23359858" NUM="103" NAME="file372.tif" MARK="NONE" DATE="-100000" ADMISSION="1"/>
<PAGE ASSIGN="\\HORNET\ImageQueue\FILE23359858" NUM="104" NAME="file373.tif" MARK="NONE" DATE="-100000" ADMISSION="1"/>
<PAGE ASSIGN="\\HORNET\ImageQueue\FILE23359858" NUM="105" NAME="file374.tif" MARK="NONE" DATE="-100000" ADMISSION="1"/>
<PAGE ASSIGN="\\HORNET\ImageQueue\FILE23359858" NUM="106" NAME="file375.tif" MARK="NONE" DATE="-100000" ADMISSION="1"/>
<PAGE ASSIGN="\\HORNET\ImageQueue\FILE23359858" NUM="107" NAME="file376.tif" MARK="NONE" DATE="-100000" ADMISSION="1"/>
<PAGE ASSIGN="\\HORNET\ImageQueue\FILE23359858" NUM="108" NAME="file377.tif" MARK="NONE" DATE="-100000" ADMISSION="1"/>
<PAGE ASSIGN="\\HORNET\ImageQueue\FILE23359858" NUM="109" NAME="file378.tif" MARK="NONE" DATE="-100000" ADMISSION="1"/>
<PAGE ASSIGN="\\HORNET\ImageQueue\FILE23359858" NUM="110" NAME="file379.tif" MARK="NONE" DATE="-100000" ADMISSION="1"/>
<PAGE ASSIGN="\\HORNET\ImageQueue\FILE23359858" NUM="111" NAME="file380.tif" MARK="NONE" DATE="-100000" ADMISSION="1"/>
<PAGE ASSIGN="\\HORNET\ImageQueue\FILE23359858" NUM="112" NAME="file381.tif" MARK="NONE" DATE="-100000" ADMISSION="1"/>
<PAGE ASSIGN="\\HORNET\ImageQueue\FILE23359858" NUM="113" NAME="file382.tif" MARK="NONE" DATE="-100000" ADMISSION="1"/>
<PAGE ASSIGN="\\HORNET\ImageQueue\FILE23359858" NUM="114" NAME="file383.tif" MARK="NONE" DATE="-100000" ADMISSION="1"/>
<PAGE ASSIGN="\\HORNET\ImageQueue\FILE23359858" NUM="115" NAME="file384.tif" MARK="NONE" DATE="-100000" ADMISSION="1"/>
<PAGE ASSIGN="\\HORNET\ImageQueue\FILE23359858" NUM="116" NAME="file385.tif" MARK="NONE" DATE="-100000" ADMISSION="1"/>
<PAGE ASSIGN="\\HORNET\ImageQueue\FILE23359858" NUM="117" NAME="file386.tif" MARK="NONE" DATE="-100000" ADMISSION="1"/>
<PAGE ASSIGN="\\HORNET\ImageQueue\FILE23359858" NUM="118" NAME="file387.tif" MARK="NONE" DATE="-100000" ADMISSION="1"/>
<PAGE ASSIGN="\\HORNET\ImageQueue\FILE23359858" NUM="119" NAME="file388.tif" MARK="NONE" DATE="-100000" ADMISSION="1"/>
<PAGE ASSIGN="\\HORNET\ImageQueue\FILE23359858" NUM="120" NAME="file389.tif" MARK="NONE" DATE="-100000" ADMISSION="1"/>
<PAGE ASSIGN="\\HORNET\ImageQueue\FILE23359858" NUM="121" NAME="file390.tif" MARK="NONE" DATE="-100000" ADMISSION="1"/>
<PAGE ASSIGN="\\HORNET\ImageQueue\FILE23359858" NUM="122" NAME="file391.tif" MARK="NONE" DATE="-100000" ADMISSION="1"/>
<PAGE ASSIGN="\\HORNET\ImageQueue\FILE23359858" NUM="123" NAME="file392.tif" MARK="NONE" DATE="-100000" ADMISSION="1"/>
<PAGE ASSIGN="\\HORNET\ImageQueue\FILE23359858" NUM="124" NAME="file393.tif" MARK="NONE" DATE="-100000" ADMISSION="1"/>
<PAGE ASSIGN="\\HORNET\ImageQueue\FILE23359858" NUM="125" NAME="file394.tif" MARK="NONE" DATE="-100000" ADMISSION="1"/>
<PAGE ASSIGN="\\HORNET\ImageQueue\FILE23359858" NUM="126" NAME="file395.tif" MARK="NONE" DATE="-100000" ADMISSION="1"/>
<PAGE ASSIGN="\\HORNET\ImageQueue\FILE23359858" NUM="127" NAME="file396.tif" MARK="NONE" DATE="-100000" ADMISSION="1"/>
<PAGE ASSIGN="\\HORNET\ImageQueue\FILE23359858" NUM="128" NAME="file397.tif" MARK="NONE" DATE="-100000" ADMISSION="1"/>
<PAGE ASSIGN="\\HORNET\ImageQueue\FILE23359858" NUM="129" NAME="file398.tif" MARK="NONE" DATE="-100000" ADMISSION="1"/>
<PAGE ASSIGN="\\HORNET\ImageQueue\FILE23359858" NUM="130" NAME="file399.tif" MARK="NONE" DATE="-100000" ADMISSION="1"/>
<PAGE ASSIGN="\\HORNET\ImageQueue\FILE23359858" NUM="131" NAME="file400.tif" MARK="NONE" DATE="-100000" ADMISSION="1"/>
<PAGE ASSIGN="\\HORNET\ImageQueue\FILE23359858" NUM="132" NAME="file401.tif" MARK="NONE" DATE="-100000" ADMISSION="1"/>
<PAGE ASSIGN="\\HORNET\ImageQueue\FILE23359858" NUM="133" NAME="file402.tif" MARK="NONE" DATE="-100000" ADMISSION="1"/>
</PAGEDATA>
